README
setup.py
ducktypes/__init__.py
ducktypes/annotate.py
ducktypes/ducktype.py
ducktypes/function_copy.py
ducktypes/instancebuilder.py
ducktypes/interface.py
ducktypes/signature.py
ducktypes/specialmethods.py
ducktypes.egg-info/PKG-INFO
ducktypes.egg-info/SOURCES.txt
ducktypes.egg-info/dependency_links.txt
ducktypes.egg-info/entry_points.txt
ducktypes.egg-info/not-zip-safe
ducktypes.egg-info/top_level.txt
ducktypes/test/__init__.py
ducktypes/test/test_annotate.py
ducktypes/test/test_ducktype.py
ducktypes/test/test_ducktype_class.py
ducktypes/test/test_function_copy.py
ducktypes/test/test_instancebuilder.py
ducktypes/test/test_signature.py
ducktypes/test/test_special_methods.py