Metadata-Version: 1.0
Name: ducktypes
Version: 0.2.5
Summary: behaviour based duck typing library
Home-page: http://ducktypes.franzoni.eu
Author: Alan Franzoni
Author-email: username@franzoni.eu
License: APL 2.0
Keywords: duck typing interfaces
Platform: UNKNOWN
